{
  "stats": {
    "suites": 1,
    "tests": 3,
    "passes": 3,
    "pending": 0,
    "failures": 0,
    "start": "2026-06-24T14:50:43.473Z",
    "end": "2026-06-24T14:50:43.477Z",
    "duration": 4,
    "testsRegistered": 3,
    "passPercent": 100,
    "pendingPercent": 0,
    "other": 0,
    "hasOther": false,
    "skipped": 0,
    "hasSkipped": false
  },
  "results": [
    {
      "uuid": "f6853669-6db6-4784-9c1d-19a31711db7f",
      "title": "",
      "fullFile": "/home/runner/work/PGATS-2026-04-trabalho-de-conclusao-integracao-continua/PGATS-2026-04-trabalho-de-conclusao-integracao-continua/test/pagamentos.test.js",
      "file": "/test/pagamentos.test.js",
      "beforeHooks": [],
      "afterHooks": [],
      "tests": [],
      "suites": [
        {
          "uuid": "313f2415-849c-4ad6-9b68-39e1dc669997",
          "title": "Teste de serviço de pagamento",
          "fullFile": "/home/runner/work/PGATS-2026-04-trabalho-de-conclusao-integracao-continua/PGATS-2026-04-trabalho-de-conclusao-integracao-continua/test/pagamentos.test.js",
          "file": "/test/pagamentos.test.js",
          "beforeHooks": [],
          "afterHooks": [],
          "tests": [
            {
              "title": "Deve registrar um pagamento com categoria padrão com valor até 100",
              "fullTitle": "Teste de serviço de pagamento Deve registrar um pagamento com categoria padrão com valor até 100",
              "timedOut": false,
              "duration": 0,
              "state": "passed",
              "speed": "fast",
              "pass": true,
              "fail": false,
              "pending": false,
              "context": null,
              "code": "const servicoDePagamento = new ServicoDePagamento();\nservicoDePagamento.pagar(\"0123-4567-8910\", \"Samar\", 100);\nconst retornoPagamento = servicoDePagamento.ultimoPagamento();\nassert.equal(retornoPagamento.codigoBarras, \"0123-4567-8910\");\nassert.equal(retornoPagamento.empresa, \"Samar\");\nassert.equal(retornoPagamento.valor, 100);\nassert.equal(retornoPagamento.categoria, \"padrão\");",
              "err": {},
              "uuid": "c971cd18-c8a1-4b13-ab56-a794cdf07e4a",
              "parentUUID": "313f2415-849c-4ad6-9b68-39e1dc669997",
              "isHook": false,
              "skipped": false
            },
            {
              "title": "Deve registrar um pagamento com categoria cara com valor acima de 100",
              "fullTitle": "Teste de serviço de pagamento Deve registrar um pagamento com categoria cara com valor acima de 100",
              "timedOut": false,
              "duration": 0,
              "state": "passed",
              "speed": "fast",
              "pass": true,
              "fail": false,
              "pending": false,
              "context": null,
              "code": "const servicoDePagamento = new ServicoDePagamento();\nservicoDePagamento.pagar(\"0123-4567-8910\", \"Intelbras\", 101);\nconst retornoPagamento = servicoDePagamento.ultimoPagamento();\nassert.equal(retornoPagamento.codigoBarras, \"0123-4567-8910\");\nassert.equal(retornoPagamento.empresa, \"Intelbras\");\nassert.equal(retornoPagamento.valor, 101);\nassert.equal(retornoPagamento.categoria, \"cara\");",
              "err": {},
              "uuid": "350e4064-77a6-49c5-a6a5-c65d035e10b8",
              "parentUUID": "313f2415-849c-4ad6-9b68-39e1dc669997",
              "isHook": false,
              "skipped": false
            },
            {
              "title": "Deve mostrar último registro de pagamento",
              "fullTitle": "Teste de serviço de pagamento Deve mostrar último registro de pagamento",
              "timedOut": false,
              "duration": 0,
              "state": "passed",
              "speed": "fast",
              "pass": true,
              "fail": false,
              "pending": false,
              "context": null,
              "code": "const servicoDePagamento = new ServicoDePagamento();\nservicoDePagamento.pagar(\"0198-7654-3210\", \"Petrobras\", 1);\nservicoDePagamento.pagar(\"0123-4567-8910\", \"Intelbras\", 1001);\nconst retornoPagamento = servicoDePagamento.ultimoPagamento();\nassert.equal(retornoPagamento.codigoBarras, \"0123-4567-8910\");\nassert.equal(retornoPagamento.empresa, \"Intelbras\");\nassert.equal(retornoPagamento.valor, 1001);\nassert.equal(retornoPagamento.categoria, \"cara\");",
              "err": {},
              "uuid": "c7dfb209-49e0-4af7-a15b-8bdfbc6cf43d",
              "parentUUID": "313f2415-849c-4ad6-9b68-39e1dc669997",
              "isHook": false,
              "skipped": false
            }
          ],
          "suites": [],
          "passes": [
            "c971cd18-c8a1-4b13-ab56-a794cdf07e4a",
            "350e4064-77a6-49c5-a6a5-c65d035e10b8",
            "c7dfb209-49e0-4af7-a15b-8bdfbc6cf43d"
          ],
          "failures": [],
          "pending": [],
          "skipped": [],
          "duration": 0,
          "root": false,
          "rootEmpty": false,
          "_timeout": 2000
        }
      ],
      "passes": [],
      "failures": [],
      "pending": [],
      "skipped": [],
      "duration": 0,
      "root": true,
      "rootEmpty": true,
      "_timeout": 2000
    }
  ],
  "meta": {
    "mocha": {
      "version": "11.7.6"
    },
    "mochawesome": {
      "options": {
        "quiet": false,
        "reportFilename": "index",
        "saveHtml": true,
        "saveJson": true,
        "consoleReporter": "spec",
        "useInlineDiffs": false,
        "code": true
      },
      "version": "7.1.4"
    },
    "marge": {
      "options": {
        "reportDir": "mochawesome-report",
        "reportFilename": "index"
      },
      "version": "6.3.2"
    }
  }
}